gobre.recipe.template-2.0-py3.9-nspkg.pth
gobre/recipe/template/__init__.py
tests/__init__.py
tests/filters.py
tests/test_recipe.py
gobre.recipe.template-2.0.dist-info/AUTHORS
gobre.recipe.template-2.0.dist-info/LICENSE
gobre.recipe.template-2.0.dist-info/METADATA
gobre.recipe.template-2.0.dist-info/WHEEL
gobre.recipe.template-2.0.dist-info/entry_points.txt
gobre.recipe.template-2.0.dist-info/namespace_packages.txt
gobre.recipe.template-2.0.dist-info/top_level.txt
gobre.recipe.template-2.0.dist-info/zip-safe
gobre.recipe.template-2.0.dist-info/RECORD
