Metadata-Version: 2.1
Name: gobre.recipe.template
Version: 2.0
Summary: Buildout recipe for making files out of Jinja2 templates
Home-page: https://github.com/gocept/gobre.recipe.template
Author: gocept
Author-email: mail@gocept.com
License: BSD
Keywords: zc.buildout recipe template Jinja2
Platform: UNKNOWN
Classifier: Framework :: Buildout
Classifier: Intended Audience :: Developers
Classifier: License :: OSI Approved :: BSD License
Classifier: Programming Language :: Python :: 3
Classifier: Programming Language :: Python :: 3.7
Classifier: Programming Language :: Python :: 3.8
Classifier: Programming Language :: Python :: 3.9
Classifier: Programming Language :: Python :: 3.10
Classifier: Programming Language :: Python :: 3.11
Classifier: Programming Language :: Python :: Implementation :: CPython
Classifier: Topic :: Software Development
Classifier: Topic :: Software Development :: Code Generators
Classifier: Topic :: Software Development :: Pre-processors
Requires-Python: >=3.7
License-File: LICENSE
License-File: AUTHORS
Requires-Dist: setuptools
Requires-Dist: zc.recipe.egg
Requires-Dist: Jinja2
Requires-Dist: zope.dottedname
